{
  "id": "07db04414722",
  "title": "From digital access to learning outcomes: India’s edtech emphasis needs to evolve",
  "description": "The Bharat Survey for EdTech shows that digital access is now widespread in India, but technologies aren’t fully understood. The focus of edtech must shift from access to structured learning and improving outcomes to deliver the human capital gains we need for Viksit Bharat.",
  "link": "https://www.livemint.com/opinion/online-views/digital-access-learning-outcomes-india-edtech-viksit-bharat-education-learning-capital-gains-11773230581359.html",
  "date": "2026-03-12",
  "source_id": "mint_opinion",
  "source_name": "Livemint - Opinion",
  "source_short": "Mint Op",
  "sectors": [
    "Digital & Technology",
    "Education",
    "Social Protection"
  ],
  "sector_slugs": [
    "digital-technology",
    "education",
    "social-protection"
  ],
  "type": "policy",
  "level": "central",
  "state": ""
}