{
  "id": "0b948774a439",
  "title": "WTO ministerial in Cameroon may discuss reforms, agriculture, e-commerce moratorium",
  "description": "The meeting is important as global trade has been disrupted first by sweeping tariffs imposed by the United States and now by the West Asia crisis triggered by the joint attack by the US and Israel on Iran",
  "link": "https://www.thehindubusinessline.com/economy/wto-ministerial-in-cameroon-may-discuss-reforms-agriculture-e-commerce-moratorium/article70719442.ece",
  "date": "2026-03-08",
  "source_id": "business_line",
  "source_name": "BusinessLine - Economy",
  "source_short": "BL",
  "sectors": [
    "Trade & Commerce",
    "Agriculture",
    "Social Protection"
  ],
  "sector_slugs": [
    "trade-commerce",
    "agriculture",
    "social-protection"
  ],
  "type": "policy",
  "level": "central",
  "state": ""
}