{
  "id": "11c9d7af16f5",
  "title": "Commercial LPG supplies in Telangana meeting only 20% demand; Uttam urges Centre for more commercial cylinders",
  "description": "",
  "link": "https://www.thehindu.com/news/national/telangana/commercial-lpg-supplies-in-telangana-meeting-only-20-demand-uttam-urges-centre-for-more-commercial-cylinders/article70744041.ece",
  "date": "2026-03-14",
  "source_id": "the_hindu_policy",
  "source_name": "The Hindu - National",
  "source_short": "The Hindu",
  "sectors": [
    "Finance & Economy"
  ],
  "sector_slugs": [
    "finance-economy"
  ],
  "type": "policy",
  "level": "central",
  "state": ""
}