{
  "id": "135ec4a917fb",
  "title": "Weather risks from possible El Nino and global tensions could pressure inflation in 2026: SBI report",
  "description": "The report noted that the Indian monsoon is influenced by both ENSO (El Nino-Southern Oscillation) and movements of the Indian Ocean Dipole (IOD)",
  "link": "https://www.thehindubusinessline.com/economy/weather-risks-from-possible-el-nino-and-global-tensions-could-pressure-inflation-in-2026-sbi-report/article70742455.ece",
  "date": "2026-03-14",
  "source_id": "business_line",
  "source_name": "BusinessLine - Economy",
  "source_short": "BL",
  "sectors": [
    "Finance & Economy",
    "Social Protection",
    "Transport & Infrastructure"
  ],
  "sector_slugs": [
    "finance-economy",
    "social-protection",
    "transport-infrastructure"
  ],
  "type": "research",
  "level": "central",
  "state": ""
}