{
  "id": "15b749c4ae69",
  "title": "Department of Commerce organizes Chintan Shivir on strengthening India’s Medical Devi...",
  "description": "Government of India press release: Department of Commerce organizes Chintan Shivir on strengthening India’s Medical Devi...",
  "link": "https://pib.gov.in/PressReleseDetail.aspx?PRID=2240258",
  "date": "2026-03-15",
  "source_id": "pib",
  "source_name": "Press Information Bureau",
  "source_short": "PIB",
  "sectors": [
    "Health",
    "Social Protection",
    "Energy"
  ],
  "sector_slugs": [
    "health",
    "social-protection",
    "energy"
  ],
  "type": "announcement",
  "level": "central",
  "state": ""
}