{
  "id": "174ce22ab67b",
  "title": "Fact Check: Is Govt Offering Free Laptops or ₹25,000 to Students?",
  "description": "A YouTube channel falsely claimed the government will give free laptops or ₹25,000 to students under the PM Laptop Scheme 2026.",
  "link": "https://www.deccanchronicle.com/fact-check/fact-check-is-govt-offering-free-laptops-or-25000-to-students-1943775",
  "date": "2026-03-14",
  "source_id": "dc_rss",
  "source_name": "Deccan Chronicle (RSS)",
  "source_short": "DC RSS",
  "sectors": [
    "Social Protection",
    "Education",
    "Digital & Technology"
  ],
  "sector_slugs": [
    "social-protection",
    "education",
    "digital-technology"
  ],
  "type": "legislation",
  "level": "central",
  "state": ""
}