{
  "id": "20f9939b0b1e",
  "title": "Parties welcome two-phase West Bengal polls; people will bring down TMC, says BJP",
  "description": "In 2021, the Assembly election in West Bengal was held in eight phases; in 2011 and 2016 there were six phases; the announcement for this year’s poll is a departure from the past",
  "link": "https://www.thehindu.com/elections/west-bengal-assembly/parties-welcome-two-phase-west-bengal-polls-people-will-bring-down-tmc-says-bjp/article70747212.ece",
  "date": "2026-03-15",
  "source_id": "the_hindu_policy",
  "source_name": "The Hindu - National",
  "source_short": "The Hindu",
  "sectors": [
    "Social Protection",
    "Governance & Reform"
  ],
  "sector_slugs": [
    "social-protection",
    "governance-reform"
  ],
  "type": "policy",
  "level": "central",
  "state": ""
}