{
  "id": "287ddf337396",
  "title": "BJP claims ₹39,000 crore of SCSP-TSP funds diverted for guarantee schemes by Congress government in Karnataka",
  "description": "BJP leader Rajkumar Patil Telkur claimed that the Siddaramaiah-led government is reportedly preparing to divert an additional ₹15,000 crore in the new budget, continuing the pattern of misallocation",
  "link": "https://www.thehindu.com/news/national/karnataka/bjp-claims-39000-crore-of-scsp-tsp-funds-diverted-for-guarantee-schemes-by-congress-government-in-karnataka/article70708356.ece",
  "date": "2026-03-06",
  "source_id": "the_hindu_policy",
  "source_name": "The Hindu - National",
  "source_short": "The Hindu",
  "sectors": [
    "Digital & Technology",
    "Finance & Economy",
    "Social Protection"
  ],
  "sector_slugs": [
    "digital-technology",
    "finance-economy",
    "social-protection"
  ],
  "type": "scheme",
  "level": "central",
  "state": ""
}