{
  "id": "346f3ce8026c",
  "title": "High-Level Committee on Banking may suggest review of CRR, SLR, licensing norms",
  "description": "The High-Level Committee on Banking may review reserve ratios, licensing norms, and strategies to boost India’s credit growth.",
  "link": "https://www.thehindubusinessline.com/economy/high-level-committee-on-banking-may-suggest-review-of-crr-slr-licensing-norms/article70735562.ece",
  "date": "2026-03-12",
  "source_id": "business_line",
  "source_name": "BusinessLine - Economy",
  "source_short": "BL",
  "sectors": [
    "Finance & Economy",
    "Digital & Technology",
    "Social Protection"
  ],
  "sector_slugs": [
    "finance-economy",
    "digital-technology",
    "social-protection"
  ],
  "type": "policy",
  "level": "central",
  "state": ""
}