{
  "id": "348d73113e72",
  "title": "Noida airport expects to handle four million passengers in CY 2026",
  "description": "NIA received an aerodrome licence from the Directorate General of Civil Aviation on March 6",
  "link": "https://www.thehindubusinessline.com/economy/logistics/noida-airport-expects-to-handle-four-million-passengers-in-cy-2026/article70739531.ece",
  "date": "2026-03-13",
  "source_id": "business_line",
  "source_name": "BusinessLine - Economy",
  "source_short": "BL",
  "sectors": [
    "Transport & Infrastructure",
    "Digital & Technology"
  ],
  "sector_slugs": [
    "transport-infrastructure",
    "digital-technology"
  ],
  "type": "policy",
  "level": "central",
  "state": ""
}