{
  "id": "3cc9cfdcd24a",
  "title": "IT ministry seeks ₹1 lakh crore for India Semiconductor Mission 2.0: Officials",
  "description": "India may allocate over ₹1 lakh crore for ISM 2.0 to boost chip design, manufacturing and supply chains, with an announcement expected by end-April",
  "link": "https://www.hindustantimes.com/india-news/it-ministry-seeks-1-lakh-crore-for-india-semiconductor-mission-2-0-officials-101773316426097.html",
  "date": "2026-03-12",
  "source_id": "hindustan_times",
  "source_name": "Hindustan Times - India",
  "source_short": "HT",
  "sectors": [
    "Digital & Technology",
    "Social Protection",
    "Labour & Employment"
  ],
  "sector_slugs": [
    "digital-technology",
    "social-protection",
    "labour-employment"
  ],
  "type": "scheme",
  "level": "central",
  "state": ""
}