{
  "id": "4172b7de43e5",
  "title": "Bhagwant Mann Flags Risk To Farmers From India-US Trade Deal",
  "description": "Bhagwant Mann on Tuesday cautioned that the interim India-US trade agreement would open India's agricultural markets to heavily subsidised American produce, which would leave farmers in Punjab and other parts of the country struggling to compete.",
  "link": "https://www.ndtv.com/india-news/bhagwant-mann-flags-risk-to-farmers-from-india-us-trade-deal-11197245#publisher=newsstand",
  "date": "2026-03-10",
  "source_id": "ndtv_india",
  "source_name": "NDTV - India",
  "source_short": "NDTV",
  "sectors": [
    "Agriculture",
    "Social Protection",
    "Trade & Commerce"
  ],
  "sector_slugs": [
    "agriculture",
    "social-protection",
    "trade-commerce"
  ],
  "type": "policy",
  "level": "central",
  "state": ""
}