{
  "id": "43de563f8679",
  "title": "Text of PM’s speech during the launch of development works in Kolkata, West Bengal",
  "description": "Government of India press release: Text of PM’s speech during the launch of development works in Kolkata, West Bengal",
  "link": "https://pib.gov.in/PressReleseDetail.aspx?PRID=2240172",
  "date": "2026-03-14",
  "source_id": "pib",
  "source_name": "Press Information Bureau",
  "source_short": "PIB",
  "sectors": [
    "Social Protection",
    "Energy"
  ],
  "sector_slugs": [
    "social-protection",
    "energy"
  ],
  "type": "announcement",
  "level": "central",
  "state": ""
}