{
  "id": "5799a314007c",
  "title": "Centre invokes Essential Commodities Act to prioritise natural gas allocation to certain sectors",
  "description": "About 30% of India’s overall natural gas consumption is routed through the Strait of Hormuz",
  "link": "https://www.thehindu.com/business/Industry/centre-invokes-essential-commodities-act-to-prioritise-natural-gas-allocation-to-certain-sectors/article70725635.ece",
  "date": "2026-03-10",
  "source_id": "the_hindu_policy",
  "source_name": "The Hindu - National",
  "source_short": "The Hindu",
  "sectors": [
    "Digital & Technology",
    "Social Protection",
    "Energy"
  ],
  "sector_slugs": [
    "digital-technology",
    "social-protection",
    "energy"
  ],
  "type": "legislation",
  "level": "central",
  "state": ""
}