{
  "id": "5a7cf529a377",
  "title": "Passenger vehicle dispatches rise 10.6% in Feb to 4,17,705 units: SIAM",
  "description": "Strong demand lifts passenger vehicle shipments, but West Asia conflict clouds outlook",
  "link": "https://www.thehindubusinessline.com/economy/passenger-vehicle-dispatches-rise-106-in-feb-to-417705-units-siam/article70738272.ece",
  "date": "2026-03-13",
  "source_id": "business_line",
  "source_name": "BusinessLine - Economy",
  "source_short": "BL",
  "sectors": [
    "Digital & Technology",
    "Social Protection"
  ],
  "sector_slugs": [
    "digital-technology",
    "social-protection"
  ],
  "type": "policy",
  "level": "central",
  "state": ""
}