{
  "id": "5b6ed570387c",
  "title": "RENEWABLE ENERGY INTEGRATION",
  "description": "Government of India press release: RENEWABLE ENERGY INTEGRATION",
  "link": "https://pib.gov.in/PressReleseDetail.aspx?PRID=2236994",
  "date": "2026-03-09",
  "source_id": "state_pib_karnataka",
  "source_name": "PIB Bengaluru (Karnataka)",
  "source_short": "PIB KA",
  "sectors": [
    "Energy",
    "Climate & Environment",
    "Social Protection"
  ],
  "sector_slugs": [
    "energy",
    "climate-environment",
    "social-protection"
  ],
  "type": "announcement",
  "level": "state",
  "state": "Karnataka"
}