{
  "id": "5c7ac0fd58a6",
  "title": "Mamata Banerjee's Big DA Move Shortly Before Bengal Poll Dates Announcement",
  "description": "West Bengal Election Dates Live Updates: Bengal Chief Minister Mamata Banerjee, less than an hour before the announcement of Model Code of Conduct, has announced Dearness Allowance or DA for thousands of state government employees.",
  "link": "https://www.ndtv.com/india-news/west-bengal-election-dates-live-updates-mamata-banerjees-big-da-move-shortly-before-bengal-poll-dates-announcement-11218147#publisher=newsstand",
  "date": "2026-03-15",
  "source_id": "ndtv_india",
  "source_name": "NDTV - India",
  "source_short": "NDTV",
  "sectors": [
    "Social Protection"
  ],
  "sector_slugs": [
    "social-protection"
  ],
  "type": "policy",
  "level": "central",
  "state": ""
}