{
  "id": "5cb88d170521",
  "title": "T20 World Cup: Sea of Blue Returns to Motera, But Vibe is Very Different From 2023 Heartbreak",
  "description": "The atmosphere around the venue is very different from November 19, 2023 when India clashed with Australia in the T20 World Cup final, and lost",
  "link": "https://www.deccanchronicle.com/sports/cricket/t20-world-cup-sea-of-blue-returns-to-motera-but-vibe-is-very-different-from-2023-heartbreak-1942364",
  "date": "2026-03-08",
  "source_id": "dc_rss",
  "source_name": "Deccan Chronicle (RSS)",
  "source_short": "DC RSS",
  "sectors": [
    "Digital & Technology",
    "Social Protection",
    "Housing"
  ],
  "sector_slugs": [
    "digital-technology",
    "social-protection",
    "housing"
  ],
  "type": "policy",
  "level": "central",
  "state": ""
}