{
  "id": "6118d857ab6b",
  "title": "'Next Time, The Forehead': Chilling Note To Badshah Found In Lawrence Bishnoi Gang's Latest Threat",
  "description": "The note specifically addressing the singer accused him of 'tarnishing the culture of Haryana'",
  "link": "https://www.news18.com/india/next-time-the-forehead-chilling-note-to-badshah-found-in-lawrence-bishnoi-gangs-latest-threat-9960829.html",
  "date": "2026-03-14",
  "source_id": "news18_india",
  "source_name": "News18 - India",
  "source_short": "News18",
  "sectors": [
    "Social Protection"
  ],
  "sector_slugs": [
    "social-protection"
  ],
  "type": "policy",
  "level": "central",
  "state": ""
}