{
  "id": "62dd589cf095",
  "title": "Policy for promoting fish farming in upstream dam and reservoir areas",
  "description": "Government of India press release: Policy for promoting fish farming in upstream dam and reservoir areas",
  "link": "https://pib.gov.in/PressReleseDetail.aspx?PRID=2238747",
  "date": "2026-03-12",
  "source_id": "pib",
  "source_name": "Press Information Bureau",
  "source_short": "PIB",
  "sectors": [
    "Social Protection",
    "Water & Sanitation"
  ],
  "sector_slugs": [
    "social-protection",
    "water-sanitation"
  ],
  "type": "announcement",
  "level": "central",
  "state": ""
}