{
  "id": "66feb9be997a",
  "title": "In Landmark Supreme Court Judgment, Ghaziabad Man Gets Right To Die",
  "description": "Harish Rana Euthanasia: Supreme Court Allows Passive Euthanasia For Ghaziabad Man In Vegetative State For 13 Years",
  "link": "https://www.ndtv.com/india-news/harish-rana-euthanasia-supreme-court-allows-passive-euthanasia-for-ghaziabad-man-in-vegetative-state-for-13-years-11198619#publisher=newsstand",
  "date": "2026-03-11",
  "source_id": "ndtv_india",
  "source_name": "NDTV - India",
  "source_short": "NDTV",
  "sectors": [
    "Social Protection",
    "Governance & Reform"
  ],
  "sector_slugs": [
    "social-protection",
    "governance-reform"
  ],
  "type": "policy",
  "level": "central",
  "state": ""
}