{
  "id": "727ec1abdfc4",
  "title": "Indian Forum In UAE Sets Up 24x7 Control Room For Stranded Indians",
  "description": "Amid the ongoing travel disruptions in the Middle East, the Indian People's Forum (IPF) has set up a 24x7 multipurpose control room in the UAE to assist stranded Indians.",
  "link": "https://www.ndtv.com/india-news/indian-forum-in-uae-sets-up-24x7-control-room-for-stranded-indians-11196839#publisher=newsstand",
  "date": "2026-03-10",
  "source_id": "ndtv_india",
  "source_name": "NDTV - India",
  "source_short": "NDTV",
  "sectors": [
    "Social Protection"
  ],
  "sector_slugs": [
    "social-protection"
  ],
  "type": "policy",
  "level": "central",
  "state": ""
}