{
  "id": "7a1aeae9b690",
  "title": "Supreme Court orders strict timeline for acid attack trials",
  "description": "The Supreme Court on Monday passed orders asking high courts across the country to set strict timelines for early completion of acid attack trials",
  "link": "https://www.hindustantimes.com/india-news/supreme-court-orders-strict-timeline-for-acid-attack-trials-101773084124217.html",
  "date": "2026-03-10",
  "source_id": "ht_rss",
  "source_name": "Hindustan Times India News (RSS)",
  "source_short": "HT RSS",
  "sectors": [
    "Governance & Reform",
    "Social Protection"
  ],
  "sector_slugs": [
    "governance-reform",
    "social-protection"
  ],
  "type": "notification",
  "level": "central",
  "state": ""
}