{
  "id": "7c42fbac1ba8",
  "title": "‘Kick his backside…’: Mani Shankar Aiyar fires retort over Pawan Khera's ‘no connection with Congress’ remark",
  "description": "Aiyar served as the Union minister for panchayati raj during the Congress-led UPA government. He was suspended from December 2017 after a controversial remark about PM Modi. The suspension was revoked August 2018",
  "link": "https://www.livemint.com/politics/news/kick-his-backside-mani-shankar-aiyar-fires-retort-over-pawan-kheras-no-connection-with-congress-remark-11771231533376.html",
  "date": "2026-02-16",
  "source_id": "livemint_policy",
  "source_name": "Livemint - Policy & Politics",
  "source_short": "Livemint",
  "sectors": [
    "Digital & Technology",
    "Energy",
    "Finance & Economy"
  ],
  "sector_slugs": [
    "digital-technology",
    "energy",
    "finance-economy"
  ],
  "type": "policy"
}