{
  "id": "828e4bf894dc",
  "title": "US grants 30-day waiver to India for Russian oil purchase as Iran conflict triggers energy concerns",
  "description": "The development comes amid concerns of a spike in energy prices due to the ongoing conflict between Iran and the US-Israel that has spilt over across the Gulf.",
  "link": "https://www.hindustantimes.com/india-news/us-waiver-india-russian-oil-buy-purchase-putin-trump-modi-energy-prices-iran-us-war-israel-west-asia-101772759613740.html",
  "date": "2026-03-06",
  "source_id": "hindustan_times",
  "source_name": "Hindustan Times - India",
  "source_short": "HT",
  "sectors": [
    "Energy",
    "Digital & Technology"
  ],
  "sector_slugs": [
    "energy",
    "digital-technology"
  ],
  "type": "policy",
  "level": "central",
  "state": ""
}