{
  "id": "82ffe0a7c748",
  "title": "SC Takes Suo Motu Cognisance of Illegal Sand Mining in National Chambal Sanctuary",
  "description": "The bench said that even areas where the Madhya Pradesh chief minister had released gharials have come under illegal mining.",
  "link": "https://www.deccanchronicle.com/nation/sc-takes-suo-motu-cognisance-of-illegal-sand-mining-in-national-chambal-sanctuary-1943520",
  "date": "2026-03-13",
  "source_id": "dc_rss",
  "source_name": "Deccan Chronicle (RSS)",
  "source_short": "DC RSS",
  "sectors": [
    "Social Protection",
    "Digital & Technology",
    "Energy"
  ],
  "sector_slugs": [
    "social-protection",
    "digital-technology",
    "energy"
  ],
  "type": "policy",
  "level": "central",
  "state": ""
}