{
  "id": "85a006ae0fbb",
  "title": "Stories Cartoons Tell: A Dialogic Analysis of Israel–Palestine Conflict",
  "description": "",
  "link": "https://www.epw.in/engage/article/stories-cartoons-tell-dialogic-analysis-israel",
  "date": "2026-03-11",
  "source_id": "epw",
  "source_name": "Economic and Political Weekly",
  "source_short": "EPW",
  "sectors": [
    "Social Protection"
  ],
  "sector_slugs": [
    "social-protection"
  ],
  "type": "research",
  "level": "central",
  "state": ""
}