{
  "id": "86138a56b3e3",
  "title": "Oracle shares jump as revenue climbs on AI demand",
  "description": "\"The demand for cloud computing for AI training and inferencing continues to grow faster than supply,\" Oracle said in the earnings report",
  "link": "https://www.thehindu.com/sci-tech/technology/oracle-shares-jump-as-revenue-climbs-on-ai-demand/article70729362.ece",
  "date": "2026-03-11",
  "source_id": "the_hindu_business",
  "source_name": "The Hindu - Business",
  "source_short": "The Hindu Biz",
  "sectors": [
    "Digital & Technology",
    "Finance & Economy",
    "Social Protection"
  ],
  "sector_slugs": [
    "digital-technology",
    "finance-economy",
    "social-protection"
  ],
  "type": "research",
  "level": "central",
  "state": ""
}