{
  "id": "8d90401275d2",
  "title": "Action to be taken for spreading rumours on fuel shortage: Assam Police",
  "description": "Action to be taken for spreading rumours on fuel shortage: Assam Police",
  "link": "https://www.hindustantimes.com/india-news/action-to-be-taken-for-spreading-rumours-on-fuel-shortage-assam-police-101773293316422.html",
  "date": "2026-03-12",
  "source_id": "hindustan_times",
  "source_name": "Hindustan Times - India",
  "source_short": "HT",
  "sectors": [
    "Governance & Reform"
  ],
  "sector_slugs": [
    "governance-reform"
  ],
  "type": "policy",
  "level": "central",
  "state": ""
}