{
  "id": "97053643b449",
  "title": "One Nation, One Election meeting: Opp would benefit from simultaneous polls, says Ghulam Nabi",
  "description": "",
  "link": "https://indianexpress.com/article/india/one-nation-one-election-meeting-opp-would-benefit-from-simultaneous-polls-says-ghulam-nabi-10573752/",
  "date": "2026-03-09",
  "source_id": "indian_express_policy",
  "source_name": "Indian Express - India",
  "source_short": "IE",
  "sectors": [
    "Digital & Technology"
  ],
  "sector_slugs": [
    "digital-technology"
  ],
  "type": "policy",
  "level": "central",
  "state": ""
}