{
  "id": "99351f767044",
  "title": "US-Israel War on Iran and Rise of African Pragmatism",
  "description": "ORF Expert Speak: US-Israel War on Iran and Rise of African Pragmatism",
  "link": "https://www.orfonline.org/expert-speak/us-israel-war-on-iran-and-rise-of-african-pragmatism",
  "date": "2026-03-15",
  "source_id": "orf",
  "source_name": "Observer Research Foundation",
  "source_short": "ORF",
  "sectors": [
    "Governance & Reform"
  ],
  "sector_slugs": [
    "governance-reform"
  ],
  "type": "policy",
  "level": "central",
  "state": ""
}