{
  "id": "a1548bdc4278",
  "title": "Announcements",
  "description": "Notification – Implementation Plan of NABH Certification Standards for  Emergency Department in Hospital 2 nd  Edition",
  "link": "https://nabh-portal-live.s3.ap-south-1.amazonaws.com/wp-content/uploads/2026/03/05180459/Notification-Implementation-Plan-of-NABH-Emergency-Certification-Standards.pdf",
  "date": "2026-03-06",
  "source_id": "nabh",
  "source_name": "NABH",
  "source_short": "NABH",
  "sectors": [
    "Health",
    "Digital & Technology",
    "Social Protection"
  ],
  "sector_slugs": [
    "health",
    "digital-technology",
    "social-protection"
  ],
  "type": "notification",
  "level": "central",
  "state": ""
}