{
  "id": "ab6879d91999",
  "title": "ମିଶନ ଶକ୍ତି ବିଭାଗ ଅଧୀନରେ କୃଷି ଓ ଅଣକୃଷି ଜୀବିକା ପ୍ରଚାର ଓ କାର୍ଯ୍ୟାନ୍ୱୟନ ପାଇଁ ସହଯୋଗ…",
  "description": "",
  "link": "https://www.odisha.gov.in/sites/default/files/2026-03/Request%20for%20Proposal%20for%20Selection%20of%20TSA%20to%20provide%20Iplementation%20Support%20in%20promotion%20of%20Farm%20and%20Non%20Farm%20livelihoods%20under%20OLM_0.pdf",
  "date": "2026-03-09",
  "source_id": "odisha_govt",
  "source_name": "Odisha Government",
  "source_short": "OD Govt",
  "sectors": [
    "Governance & Reform"
  ],
  "sector_slugs": [
    "governance-reform"
  ],
  "type": "policy",
  "level": "central",
  "state": ""
}