{
  "id": "af4c7b2f1324",
  "title": "Supreme Court says if BNS treats ‘administering’ acid as separate offence, RPwD Act must too",
  "description": "When BNS distinguishes between throwing and administering, the aspect of administration requires to be articulated in the RPwD Act also, observes Justice Bagchi",
  "link": "https://www.thehindu.com/news/national/supreme-court-says-if-bns-treats-administering-acid-as-separate-offence-rpwd-act-must-too/article70723163.ece",
  "date": "2026-03-09",
  "source_id": "the_hindu_policy",
  "source_name": "The Hindu - National",
  "source_short": "The Hindu",
  "sectors": [
    "Social Protection",
    "Governance & Reform",
    "Disability & Inclusion"
  ],
  "sector_slugs": [
    "social-protection",
    "governance-reform",
    "disability-inclusion"
  ],
  "type": "legislation",
  "level": "central",
  "state": ""
}