{
  "id": "b4bd699c7f65",
  "title": "No parking fee in stand-alone cinema theatres: HC",
  "description": "",
  "link": "https://www.thehindu.com/news/national/telangana/no-parking-fee-in-stand-alone-cinema-theatres-hc/article70732117.ece",
  "date": "2026-03-11",
  "source_id": "the_hindu_policy",
  "source_name": "The Hindu - National",
  "source_short": "The Hindu",
  "sectors": [
    "Social Protection",
    "Urban Development"
  ],
  "sector_slugs": [
    "social-protection",
    "urban-development"
  ],
  "type": "policy",
  "level": "central",
  "state": ""
}