{
  "id": "b5464db1a3c5",
  "title": "Moinabad Farmhouse Becomes Centre Of Raids",
  "description": "Updated Karma strikes back hard, says BJP",
  "link": "https://www.deccanchronicle.com/southern-states/telangana/moinabad-farmhouse-becomes-centre-of-raids-1944058",
  "date": "2026-03-15",
  "source_id": "dc_rss",
  "source_name": "Deccan Chronicle (RSS)",
  "source_short": "DC RSS",
  "sectors": [
    "Digital & Technology",
    "Social Protection"
  ],
  "sector_slugs": [
    "digital-technology",
    "social-protection"
  ],
  "type": "policy",
  "level": "central",
  "state": ""
}