{
  "id": "b57c9ec3a99a",
  "title": "Haryana CM accuses AAP government in Punjab of indulging in ‘election-time freebie politics’",
  "description": "Responding to the Punjab government’s budget announcement of providing ₹1,500 to women from the SC category and ₹1,000 to other women, Haryana CM said the AAP government is making these announcements with the upcoming Assembly elections in mind.",
  "link": "https://www.thehindu.com/news/national/punjab/haryana-cm-accuses-aap-government-in-punjab-of-indulging-in-election-time-freebie-politics/article70722862.ece",
  "date": "2026-03-10",
  "source_id": "the_hindu_policy",
  "source_name": "The Hindu - National",
  "source_short": "The Hindu",
  "sectors": [
    "Digital & Technology",
    "Finance & Economy",
    "Social Protection"
  ],
  "sector_slugs": [
    "digital-technology",
    "finance-economy",
    "social-protection"
  ],
  "type": "budget",
  "level": "central",
  "state": ""
}