{
  "id": "bf80b4e6ecab",
  "title": "Empanelment of AMC",
  "description": "",
  "link": "https://www.seci.co.in/uploads/news/1773062125_Empanelment_with_an_Asset_Management_Company_(AMC).pdf",
  "date": "2026-03-09",
  "source_id": "seci",
  "source_name": "Solar Energy Corporation of India",
  "source_short": "SECI",
  "sectors": [
    "Energy",
    "Climate & Environment"
  ],
  "sector_slugs": [
    "energy",
    "climate-environment"
  ],
  "type": "policy",
  "level": "central",
  "state": ""
}