{
  "id": "c098ce679f3a",
  "title": "A Dark Night: India-Bound Oil Tanker's Daring Dash Through Strait Of Hormuz",
  "description": "Amid escalating tensions in the Middle East, a Liberian-flagged tanker, carrying crude oil from Saudi Arabia, has berthed at the Mumbai Port, becoming the first vessel to safely transit the Gulf waterway and arrive in India amid war.",
  "link": "https://www.ndtv.com/world-news/iran-war-news-how-india-bound-oil-tanker-crossed-war-hit-strait-of-hormuz-a-dark-tale-11204597#publisher=newsstand",
  "date": "2026-03-12",
  "source_id": "ndtv_india",
  "source_name": "NDTV - India",
  "source_short": "NDTV",
  "sectors": [
    "Digital & Technology",
    "Social Protection",
    "Water & Sanitation"
  ],
  "sector_slugs": [
    "digital-technology",
    "social-protection",
    "water-sanitation"
  ],
  "type": "policy",
  "level": "central",
  "state": ""
}