{
  "id": "c20682f44dd8",
  "title": "Australia Weighs Request From Gulf Nations for Military Support",
  "description": "Australia said it is assessing a request from Gulf nations for defensive military support to protect them against Iranian drone and missile attacks.",
  "link": "https://www.livemint.com/politics/australia-weighs-request-from-gulf-nations-for-military-support-11772929660056.html",
  "date": "2026-03-08",
  "source_id": "livemint_rss",
  "source_name": "Livemint Politics (RSS)",
  "source_short": "Mint RSS",
  "sectors": [
    "Digital & Technology",
    "Defence & Security",
    "Social Protection"
  ],
  "sector_slugs": [
    "digital-technology",
    "defence-security",
    "social-protection"
  ],
  "type": "policy",
  "level": "central",
  "state": ""
}