{
  "id": "c4d52f2b16f4",
  "title": "Inter-Ministerial Briefing on recent Developments in West Asia",
  "description": "Government of India press release: Inter-Ministerial Briefing on recent Developments in West Asia",
  "link": "https://pib.gov.in/PressReleseDetail.aspx?PRID=2239172",
  "date": "2026-03-12",
  "source_id": "pib",
  "source_name": "Press Information Bureau",
  "source_short": "PIB",
  "sectors": [
    "Social Protection",
    "Energy"
  ],
  "sector_slugs": [
    "social-protection",
    "energy"
  ],
  "type": "announcement",
  "level": "central",
  "state": ""
}