{
  "id": "d02deb7bd2f6",
  "title": "Kharge seeks discussion on West Asia; irresponsible behaviour, says Nadda",
  "description": "",
  "link": "https://indianexpress.com/article/india/kharge-seeks-discussion-on-west-asia-irresponsible-behaviour-says-nadda-10573757/",
  "date": "2026-03-09",
  "source_id": "indian_express_policy",
  "source_name": "Indian Express - India",
  "source_short": "IE",
  "sectors": [
    "Social Protection"
  ],
  "sector_slugs": [
    "social-protection"
  ],
  "type": "policy",
  "level": "central",
  "state": ""
}