{
  "id": "d25ad9ce9c09",
  "title": "Airlines Making Arrangements In Response To Middle East Situation: Centre",
  "description": "The Civil Aviation Ministry said it is closely monitoring developments in Middle East and their potential implications for air travel between India and the region.",
  "link": "https://www.ndtv.com/india-news/middle-east-war-iran-israel-conflict-airlines-making-arrangements-in-response-to-situation-centre-11197346#publisher=newsstand",
  "date": "2026-03-11",
  "source_id": "ndtv_india",
  "source_name": "NDTV - India",
  "source_short": "NDTV",
  "sectors": [
    "Digital & Technology",
    "Finance & Economy",
    "Social Protection"
  ],
  "sector_slugs": [
    "digital-technology",
    "finance-economy",
    "social-protection"
  ],
  "type": "policy",
  "level": "central",
  "state": ""
}