{
  "id": "d8ff89daa4af",
  "title": "Ranbir–Kat To Reunite In ‘Raajneeti 2",
  "description": "Director Prakash Jha says the story will again draw inspiration from the Mahabharata",
  "link": "https://www.deccanchronicle.com/tabloid/hyderabad-chronicle/ranbirkat-to-reunite-in-raajneeti-2-1944081",
  "date": "2026-03-15",
  "source_id": "dc_rss",
  "source_name": "Deccan Chronicle (RSS)",
  "source_short": "DC RSS",
  "sectors": [
    "Digital & Technology",
    "Social Protection"
  ],
  "sector_slugs": [
    "digital-technology",
    "social-protection"
  ],
  "type": "policy",
  "level": "central",
  "state": ""
}