{
  "id": "df4a671eba93",
  "title": "Prolonged Screen Exposure Steals Our Sleep",
  "description": "The survey found that 82.6 per cent of respondents use AI tools daily or multiple times a day, while 59.1 per cent spend more than four hours on screens, underscoring how deeply digital tools have entered everyday routines.",
  "link": "https://www.deccanchronicle.com/southern-states/telangana/prolonged-screen-exposure-steals-our-sleep-1943952",
  "date": "2026-03-14",
  "source_id": "dc_rss",
  "source_name": "Deccan Chronicle (RSS)",
  "source_short": "DC RSS",
  "sectors": [
    "Digital & Technology",
    "Social Protection",
    "Energy"
  ],
  "sector_slugs": [
    "digital-technology",
    "social-protection",
    "energy"
  ],
  "type": "policy",
  "level": "central",
  "state": ""
}