{
  "id": "e3b88397969d",
  "title": "India in touch with Iran for safe passage of vessels through Strait of Hormuz",
  "description": "India engages Iran in diplomatic talks seeking safe passage for vessels through the vital Strait of Hormuz amid heightened tensions and attacks on shipping",
  "link": "https://www.hindustantimes.com/india-news/india-in-touch-with-iran-for-safe-passage-of-vessels-through-strait-of-hormuz-101773328730738.html",
  "date": "2026-03-12",
  "source_id": "hindustan_times",
  "source_name": "Hindustan Times - India",
  "source_short": "HT",
  "sectors": [
    "Digital & Technology",
    "Social Protection",
    "Transport & Infrastructure"
  ],
  "sector_slugs": [
    "digital-technology",
    "social-protection",
    "transport-infrastructure"
  ],
  "type": "policy",
  "level": "central",
  "state": ""
}