{
  "id": "e48e632cd0c3",
  "title": "Caught on CCTV: Elderly dragged, beaten by neighbours over fence dispute in UP",
  "description": "Caught on CCTV: Elderly dragged, beaten by neighbours over fence dispute in UP",
  "link": "https://www.indiatoday.in/india/story/uttar-pradesh-alwar-neighbours-attack-women-thrashed-cctv-video-fence-2880806-2026-03-12?utm_source=rss",
  "date": "2026-03-12",
  "source_id": "indiatoday_rss",
  "source_name": "India Today (RSS)",
  "source_short": "IT RSS",
  "sectors": [
    "Governance & Reform"
  ],
  "sector_slugs": [
    "governance-reform"
  ],
  "type": "policy",
  "level": "central",
  "state": ""
}