{
  "id": "e4b59b79341a",
  "title": "कश्मीर के गांदरबल में पेंशनभोगी सहायता कार्यक्रम और श्रीनगर में बीएसएनएल पेंशनभोगियों के लिए उप-कार्यालय खोलने की प्रक्रिया की शुरुआत",
  "description": "",
  "link": "https://pib.gov.in/PressReleaseIframePage.aspx?PRID=2239705",
  "date": "2026-03-13",
  "source_id": "pib_rss",
  "source_name": "PIB RSS Feed",
  "source_short": "PIB RSS",
  "sectors": [
    "Governance & Reform"
  ],
  "sector_slugs": [
    "governance-reform"
  ],
  "type": "policy",
  "level": "central",
  "state": ""
}