{
  "id": "e81815bd67e0",
  "title": "HYDRAA Saves Park Land From Encroachers",
  "description": "HYDRAA confirmed the land was designated as park space in the approved layout",
  "link": "https://www.deccanchronicle.com/southern-states/telangana/hydraa-saves-park-land-from-encroachers-1942953",
  "date": "2026-03-10",
  "source_id": "dc_rss",
  "source_name": "Deccan Chronicle (RSS)",
  "source_short": "DC RSS",
  "sectors": [
    "Labour & Employment",
    "Defence & Security",
    "Science & Innovation"
  ],
  "sector_slugs": [
    "labour-employment",
    "defence-security",
    "science-innovation"
  ],
  "type": "policy",
  "level": "central",
  "state": ""
}