{
  "id": "e9ee16ef0bad",
  "title": "Sadanand Date takes charge as SEBI Executive Director, to oversee investigations",
  "description": "Sadanand S Date has taken charge as Executive Director at the Securities and Exchange Board of India (SEBI) and will oversee the regulator’s Investigations Department, the market watchdog said in a press release on Friday.Date assumed office in Mumbai on March 4.An Indian Police Service (IPS) officer belonging to the 2007 batch from the Uttarakhand cadre, Date is joining SEBI after serving on central deputation with the Central Bureau of Investigation (CBI).During his tenure with the CBI in Mumb",
  "link": "https://www.barandbench.com/news/law-policy/sadanand-date-takes-charge-as-sebi-executive-director-to-oversee-investigations",
  "date": "2026-03-14",
  "source_id": "barandbench",
  "source_name": "Bar and Bench",
  "source_short": "Bar&Bench",
  "sectors": [
    "Digital & Technology",
    "Finance & Economy",
    "Social Protection"
  ],
  "sector_slugs": [
    "digital-technology",
    "finance-economy",
    "social-protection"
  ],
  "type": "announcement",
  "level": "central",
  "state": ""
}