{
  "id": "f519095bcd2b",
  "title": "Karnataka budget announces AI tutor for 1.2 million students",
  "description": "Karnataka's 2026-27 Budget includes AI education initiatives, a digital tutor for students, and a new robotics campus",
  "link": "https://www.hindustantimes.com/india-news/karnataka-budget-announces-ai-tutor-for-1-2-million-students-101772826097909.html",
  "date": "2026-03-07",
  "source_id": "hindustan_times",
  "source_name": "Hindustan Times - India",
  "source_short": "HT",
  "sectors": [
    "Digital & Technology",
    "Education",
    "Finance & Economy"
  ],
  "sector_slugs": [
    "digital-technology",
    "education",
    "finance-economy"
  ],
  "type": "budget",
  "level": "central",
  "state": ""
}