{
  "id": "f756bfba2d0f",
  "title": "Protest staged in Kalaburagi against hike in LPG prices",
  "description": "Congress Women’s Wing members express strong dissent against the recent surge in LPG prices",
  "link": "https://www.thehindu.com/news/national/karnataka/protest-staged-in-kalaburagi-against-hike-in-lpg-prices/article70723376.ece",
  "date": "2026-03-09",
  "source_id": "the_hindu_policy",
  "source_name": "The Hindu - National",
  "source_short": "The Hindu",
  "sectors": [
    "Digital & Technology",
    "Social Protection",
    "Gender & Women"
  ],
  "sector_slugs": [
    "digital-technology",
    "social-protection",
    "gender-women"
  ],
  "type": "policy",
  "level": "central",
  "state": ""
}