{
  "id": "fb1baada32be",
  "title": "ICTPL Sets Record Eith 19,150 Tonnes Manganese Ore Loading At Vizag Port",
  "description": "The company said the achievement highlights ICTPL’s operational efficiency and coordinated teamwork in handling bulk cargo operations",
  "link": "https://www.deccanchronicle.com/southern-states/andhra-pradesh/ictpl-sets-record-eith-19150-tonnes-manganese-ore-loading-at-vizag-port-1943237",
  "date": "2026-03-11",
  "source_id": "dc_rss",
  "source_name": "Deccan Chronicle (RSS)",
  "source_short": "DC RSS",
  "sectors": [
    "Digital & Technology",
    "Social Protection",
    "Energy"
  ],
  "sector_slugs": [
    "digital-technology",
    "social-protection",
    "energy"
  ],
  "type": "policy",
  "level": "central",
  "state": ""
}